chess_gen.py
chess_gen-1.2.2.dist-info/entry_points.txt
chess_gen-1.2.2.dist-info/licenses/LICENSE
chess_gen-1.2.2.dist-info/WHEEL
chess_gen-1.2.2.dist-info/METADATA
chess_gen-1.2.2.dist-info/RECORD
