Metadata-Version: 2.4
Name: chess-gen
Version: 1.2.2
Summary: Generate chess positions and practise on Lichess.
Author: Stanislav Schmidt
Requires-Python: >=3.9
Classifier: License :: OSI Approved :: MIT License
License-File: LICENSE
Requires-Dist: chess
Requires-Dist: rich
Requires-Dist: flit ; extra == "dev"
Requires-Dist: mypy ; extra == "dev"
Requires-Dist: ruff ; extra == "dev"
Project-URL: Documentation, https://github.com/Stannislav/chess-gen
Project-URL: Home, https://github.com/Stannislav/chess-gen
Project-URL: Source, https://github.com/Stannislav/chess-gen
Provides-Extra: dev
